{"mode":"advanced","appURL":"http://board.apex.rest/ords/f?p=101:1","srcFolder":"/Users/avhrst/Developer/veloliga/src","distFolder":"/Users/avhrst/Developer/veloliga/dist","js":{"processor":"default","concat":true,"concatFilename":"app","library":false,"tsConcat":false},"css":{"language":"css","concat":true,"concatFilename":"app","sassIncludePath":"/Users/avhrst/Developer/Divosvit/src/sass"},"browsersync":{"notify":true,"ghostMode":false},"header":{"enabled":false},"apex":{"openBuilder":false},"publish":{"destination":"application","path":"/Users/avhrst/sqlcl/bin/sql","connectionType":"basic","username":"veloliga","password":"AvhrSt","host":"board.apex.rest","port":"1521","basicType":"sid","sid":"xe"}}